weread2notionpro/__init__.py
weread2notionpro/__main__.py
weread2notionpro/book.py
weread2notionpro/config.py
weread2notionpro/fix.py
weread2notionpro/notion_helper.py
weread2notionpro/read_time.py
weread2notionpro/utils.py
weread2notionpro/weread.py
weread2notionpro/weread2notion.py
weread2notionpro/weread_api.py
weread2notionpro-0.6.8.dist-info/METADATA
weread2notionpro-0.6.8.dist-info/WHEEL
weread2notionpro-0.6.8.dist-info/entry_points.txt
weread2notionpro-0.6.8.dist-info/top_level.txt
weread2notionpro-0.6.8.dist-info/RECORD
