Metadata-Version: 2.1
Name: weread2notionpro
Version: 0.6.8
Summary: 自动将微信读书笔记和阅读记录同步到Notion
Home-page: https://github.com/malinkang/weread2notion-pro
Author: malinkang
Author-email: linkang.ma@gmail.com
Classifier: Programming Language :: Python :: 3
Classifier: License :: OSI Approved :: MIT License
Classifier: Operating System :: OS Independent
Requires-Python: >=3.6
Requires-Dist: requests
Requires-Dist: pendulum
Requires-Dist: retrying
Requires-Dist: notion-client
Requires-Dist: github-heatmap
